LICENSE
README.md
setup.cfg
setup.py
beam_bc365/__init__.py
beam_bc365.egg-info/PKG-INFO
beam_bc365.egg-info/SOURCES.txt
beam_bc365.egg-info/dependency_links.txt
beam_bc365.egg-info/requires.txt
beam_bc365.egg-info/top_level.txt
beam_bc365/io/__init__.py
beam_bc365/io/bc_service.py
beam_bc365/io/bc_service_api.py