Metadata-Version: 2.1
Name: beam-bc365
Version: 0.3.0
Summary: Microsoft Business Central transofrm for the Apache beam python SDK.
Home-page: https://github.com/Spazzy757/beam-bc365
Author: Brendan Kamp
Author-email: brendankamp757@gmail.com
License: UNKNOWN
Platform: UNKNOWN
Classifier: Programming Language :: Python
Classifier: Programming Language :: Python :: 3
Classifier: License :: OSI Approved :: MIT License
Classifier: Operating System :: OS Independent
Provides-Extra: dev
